{
  "generated_at": "2026-05-27T17:56:11.437Z",
  "sync_type": "targeted-pending-sources",
  "duration_ms": 2712,
  "pending_file": "/home/runner/work/thealgorithmwitch.github.io/thealgorithmwitch.github.io/resources/jobs/pending-synced-jobs.json",
  "source_health_written": true,
  "deprecated_pending_entries_removed": 0,
  "target_source_ids": [],
  "adapter_gap_source_ids": [],
  "summary": {
    "sources_attempted": 0,
    "jobs_found": 0,
    "jobs_normalized": 0,
    "relevance_matched_count": 0,
    "active_review_added": 0,
    "backlog_added": 0,
    "backlog_preserved": 0,
    "resurfaced_from_backlog": 0,
    "stale_backlog_archived": 0,
    "repeat_surface_prevented_count": 0,
    "capped_existing": 0,
    "jobs_added_to_pending": 0,
    "capped_count": 0,
    "skipped_low_relevance_count": 0,
    "duplicates_skipped": 0,
    "deprecated_pending_entries_removed": 0,
    "skipped_reasons": {}
  },
  "results": []
}
